LICENSE
README.md
examples/client_example.py
examples/server_example.py
py_udp/__init__.py
py_udp/_py_udp.cp312-win_amd64.pyd
py_udp_rust-0.2.0.dist-info/METADATA
py_udp_rust-0.2.0.dist-info/WHEEL
py_udp_rust-0.2.0.dist-info/entry_points.txt
py_udp_rust-0.2.0.dist-info/licenses/LICENSE
tests/test_udp.py
py_udp_rust-0.2.0.dist-info/RECORD
