Metadata-Version: 2.4
Name: py-udp-rust
Version: 0.2.0
Classifier: Development Status :: 4 - Beta
Classifier: Intended Audience :: Developers
Classifier: License :: OSI Approved :: MIT License
Classifier: Operating System :: OS Independent
Classifier: Programming Language :: Python :: 3
Classifier: Programming Language :: Python :: 3.12
Classifier: Programming Language :: Python :: Implementation :: CPython
Classifier: Programming Language :: Rust
Classifier: Topic :: Internet
Classifier: Topic :: Software Development :: Libraries :: Python Modules
Classifier: Topic :: System :: Networking
Requires-Dist: pytest-coverage>=0.0
Requires-Dist: typing-extensions>=4.0.0
Requires-Dist: pytest>=7.0.0 ; extra == 'dev'
Requires-Dist: pytest-asyncio>=0.21.0 ; extra == 'dev'
Requires-Dist: black>=23.0.0 ; extra == 'dev'
Requires-Dist: isort>=5.12.0 ; extra == 'dev'
Requires-Dist: mypy>=1.0.0 ; extra == 'dev'
Provides-Extra: dev
License-File: LICENSE
Summary: High-performance UDP networking library for Python with Rust backend
Keywords: udp,networking,rust,async,socket,server,client
Author-email: Ravil Shakerov <xellaopromaster@yandex.ru>
Maintainer-email: Ravil Shakerov <xellaopromaster@yandex.ru>
License: MIT
Requires-Python: >=3.12
Project-URL: Homepage, https://github.com/DaymaNKinG990/py-udp
Project-URL: Documentation, https://github.com/DaymaNKinG990/py-udp#readme
Project-URL: Repository, https://github.com/DaymaNKinG990/py-udp
Project-URL: Issues, https://github.com/DaymaNKinG990/py-udp/issues
Project-URL: Changelog, https://github.com/DaymaNKinG990/py-udp/blob/main/CHANGELOG.md
